LICENSE
MANIFEST.in
README
README.md
setup.cfg
setup.py
pyiArduinoI2Csht/__init__.py
pyiArduinoI2Csht/iarduino_I2C_PI.cpp
pyiArduinoI2Csht/iarduino_I2C_PI.h
pyiArduinoI2Csht/iarduino_I2C_SHT.cpp
pyiArduinoI2Csht/iarduino_I2C_SHT.h
pyiArduinoI2Csht/iarduino_I2C_SHT.pxd
pyiArduinoI2Csht/pyiArduinoI2Csht.cpp
pyiArduinoI2Csht/pyiArduinoI2Csht.pyx
pyiArduinoI2Csht/setup.py
pyiArduinoI2Csht.egg-info/PKG-INFO
pyiArduinoI2Csht.egg-info/SOURCES.txt
pyiArduinoI2Csht.egg-info/dependency_links.txt
pyiArduinoI2Csht.egg-info/top_level.txt
pyiArduinoI2Csht/cpp/FindDevices.cpp
pyiArduinoI2Csht/cpp/NewAddress.cpp
pyiArduinoI2Csht/cpp/getAll.cpp
pyiArduinoI2Csht/cpp/getAllChanged.cpp
pyiArduinoI2Csht/cpp/setPeriod.cpp
pyiArduinoI2Csht/examples/FindDevices.py
pyiArduinoI2Csht/examples/getAll.py
pyiArduinoI2Csht/examples/getAllChanged.py
pyiArduinoI2Csht/examples/newAddress.py
pyiArduinoI2Csht/examples/setPeriod.py